{"0:0:3:82:84": {"defined_list": ["noxa"], "percent_pass_filter": 0.132}, "0:0:3:82:93": {"defined_list": ["clam"], "percent_pass_filter": 0.116}, "0:0:3:82:99": {"defined_list": ["chic"], "percent_pass_filter": 0.119}, "0:0:3:82:114": {"defined_list": ["cool"], "percent_pass_filter": 0.094}, "0:0:3:82:140": {"defined_list": ["site"], "percent_pass_filter": 0.103}, "0:0:3:82:207": {"defined_list": ["piss"], "percent_pass_filter": 0.161}, "0:0:3:82:237": {"defined_list": ["algum"], "percent_pass_filter": 0.165}, "0:0:3:82:262": {"defined_list": ["maim"], "percent_pass_filter": 0.182}, "0:0:3:82:271": {"defined_list": ["lilt"], "percent_pass_filter": 0.122}, "0:0:3:82:301": {"defined_list": ["soja"], "percent_pass_filter": 0.122}, "0:0:3:82:329": {"defined_list": ["nuke"], "percent_pass_filter": 0.136}, "0:0:3:82:371": {"defined_list": ["wowt"], "percent_pass_filter": 0.119}, "0:0:3:82:375": {"defined_list": ["gaff"], "percent_pass_filter": 0.168}}