{"0:0:4:6:14": {"defined_list": ["fowk"], "percent_pass_filter": 0.157}, "0:0:4:6:45": {"defined_list": ["cond"], "percent_pass_filter": 0.136}, "0:0:4:6:59": {"defined_list": ["urus"], "percent_pass_filter": 0.14}, "0:0:4:6:152": {"defined_list": ["kame"], "percent_pass_filter": 0.107}, "0:0:4:6:205": {"defined_list": ["aten"], "percent_pass_filter": 0.093}, "0:0:4:6:213": {"defined_list": ["fool"], "percent_pass_filter": 0.198}, "0:0:4:6:236": {"defined_list": ["pavo"], "percent_pass_filter": 0.174}, "0:0:4:6:239": {"defined_list": ["towy"], "percent_pass_filter": 0.153}, "0:0:4:6:300": {"defined_list": ["mamo"], "percent_pass_filter": 0.112}, "0:0:4:6:328": {"defined_list": ["thee"], "percent_pass_filter": 0.153}, "0:0:4:6:351": {"defined_list": ["duke"], "percent_pass_filter": 0.13}, "0:0:4:6:358": {"defined_list": ["foci"], "percent_pass_filter": 0.152}, "0:0:4:6:384": {"defined_list": ["seme"], "percent_pass_filter": 0.141}, "0:0:4:6:390": {"defined_list": ["rule"], "percent_pass_filter": 0.123}}