{"0:0:3:11:9": {"defined_list": ["jong"], "percent_pass_filter": 0.161}, "0:0:3:11:68": {"defined_list": ["pawer"], "percent_pass_filter": 0.142}, "0:0:3:11:121": {"defined_list": ["akal"], "percent_pass_filter": 0.116}, "0:0:3:11:141": {"defined_list": ["aira"], "percent_pass_filter": 0.131}, "0:0:3:11:198": {"defined_list": ["zone"], "percent_pass_filter": 0.116}, "0:0:3:11:234": {"defined_list": ["knur"], "percent_pass_filter": 0.156}, "0:0:3:11:286": {"defined_list": ["spor"], "percent_pass_filter": 0.109}, "0:0:3:11:364": {"defined_list": ["dale"], "percent_pass_filter": 0.184}, "0:0:3:11:394": {"defined_list": ["knar"], "percent_pass_filter": 0.109}, "0:0:3:11:402": {"defined_list": ["izle"], "percent_pass_filter": 0.126}}