{"0:0:1:29:5": {"defined_list": ["mime"], "percent_pass_filter": 0.183}, "0:0:1:29:38": {"defined_list": ["tawn"], "percent_pass_filter": 0.151}, "0:0:1:29:63": {"defined_list": ["coif"], "percent_pass_filter": 0.155}, "0:0:1:29:78": {"defined_list": ["pram"], "percent_pass_filter": 0.185}, "0:0:1:29:112": {"defined_list": ["haec"], "percent_pass_filter": 0.091}, "0:0:1:29:129": {"defined_list": ["raiae"], "percent_pass_filter": 0.157}, "0:0:1:29:190": {"defined_list": ["gaut"], "percent_pass_filter": 0.073}, "0:0:1:29:249": {"defined_list": ["coff"], "percent_pass_filter": 0.138}, "0:0:1:29:275": {"defined_list": ["erth"], "percent_pass_filter": 0.162}, "0:0:1:29:352": {"defined_list": ["wudu"], "percent_pass_filter": 0.133}, "0:0:1:29:356": {"defined_list": ["plud"], "percent_pass_filter": 0.11}, "0:0:1:29:401": {"defined_list": ["flux"], "percent_pass_filter": 0.135}}