{"0:0:2:12:66": {"defined_list": ["genu"], "percent_pass_filter": 0.175}, "0:0:2:12:69": {"defined_list": ["crare"], "percent_pass_filter": 0.117}, "0:0:2:12:73": {"defined_list": ["hove"], "percent_pass_filter": 0.08}, "0:0:2:12:96": {"defined_list": ["ride"], "percent_pass_filter": 0.126}, "0:0:2:12:131": {"defined_list": ["muff"], "percent_pass_filter": 0.134}, "0:0:2:12:263": {"defined_list": ["ordu"], "percent_pass_filter": 0.156}, "0:0:2:12:329": {"defined_list": ["ayah"], "percent_pass_filter": 0.128}, "0:0:2:12:332": {"defined_list": ["apina"], "percent_pass_filter": 0.13}, "0:0:2:12:370": {"defined_list": ["paar"], "percent_pass_filter": 0.148}}