{"0:0:1:51:39": {"defined_list": ["amil"], "percent_pass_filter": 0.083}, "0:0:1:51:46": {"defined_list": ["moro"], "percent_pass_filter": 0.146}, "0:0:1:51:49": {"defined_list": ["flan"], "percent_pass_filter": 0.109}, "0:0:1:51:78": {"defined_list": ["ryot"], "percent_pass_filter": 0.156}, "0:0:1:51:90": {"defined_list": ["clow"], "percent_pass_filter": 0.088}, "0:0:1:51:91": {"defined_list": ["biga"], "percent_pass_filter": 0.138}, "0:0:1:51:134": {"defined_list": ["tiou"], "percent_pass_filter": 0.165}, "0:0:1:51:188": {"defined_list": ["juju"], "percent_pass_filter": 0.126}, "0:0:1:51:387": {"defined_list": ["axon"], "percent_pass_filter": 0.158}, "0:0:1:51:392": {"defined_list": ["roan"], "percent_pass_filter": 0.14}, "0:0:1:51:394": {"defined_list": ["thew"], "percent_pass_filter": 0.206}}