{"0:0:2:83:2": {"defined_list": ["dook"], "percent_pass_filter": 0.161}, "0:0:2:83:4": {"defined_list": ["galp"], "percent_pass_filter": 0.122}, "0:0:2:83:40": {"defined_list": ["snog"], "percent_pass_filter": 0.137}, "0:0:2:83:147": {"defined_list": ["hoga"], "percent_pass_filter": 0.116}, "0:0:2:83:152": {"defined_list": ["numb"], "percent_pass_filter": 0.133}, "0:0:2:83:179": {"defined_list": ["tapu"], "percent_pass_filter": 0.104}, "0:0:2:83:200": {"defined_list": ["sare"], "percent_pass_filter": 0.178}, "0:0:2:83:236": {"defined_list": ["tunk"], "percent_pass_filter": 0.186}, "0:0:2:83:241": {"defined_list": ["cary"], "percent_pass_filter": 0.13}, "0:0:2:83:246": {"defined_list": ["peso"], "percent_pass_filter": 0.15}, "0:0:2:83:253": {"defined_list": ["roka"], "percent_pass_filter": 0.162}, "0:0:2:83:277": {"defined_list": ["dern"], "percent_pass_filter": 0.194}, "0:0:2:83:285": {"defined_list": ["wore"], "percent_pass_filter": 0.152}, "0:0:2:83:286": {"defined_list": ["meng"], "percent_pass_filter": 0.105}, "0:0:2:83:323": {"defined_list": ["rolf"], "percent_pass_filter": 0.16}, "0:0:2:83:344": {"defined_list": ["pled"], "percent_pass_filter": 0.143}, "0:0:2:83:358": {"defined_list": ["wull"], "percent_pass_filter": 0.171}, "0:0:2:83:378": {"defined_list": ["jank"], "percent_pass_filter": 0.165}}