{"0:0:0:39:5": {"defined_list": ["pick"], "percent_pass_filter": 0.121}, "0:0:0:39:19": {"defined_list": ["ides"], "percent_pass_filter": 0.167}, "0:0:0:39:45": {"defined_list": ["sake"], "percent_pass_filter": 0.133}, "0:0:0:39:128": {"defined_list": ["ease"], "percent_pass_filter": 0.16}, "0:0:0:39:134": {"defined_list": ["saum"], "percent_pass_filter": 0.11}, "0:0:0:39:145": {"defined_list": ["tuft"], "percent_pass_filter": 0.135}, "0:0:0:39:150": {"defined_list": ["cara"], "percent_pass_filter": 0.134}, "0:0:0:39:156": {"defined_list": ["nair"], "percent_pass_filter": 0.16}, "0:0:0:39:163": {"defined_list": ["will"], "percent_pass_filter": 0.11}, "0:0:0:39:167": {"defined_list": ["lucy"], "percent_pass_filter": 0.17}, "0:0:0:39:171": {"defined_list": ["bail"], "percent_pass_filter": 0.203}, "0:0:0:39:172": {"defined_list": ["lieu"], "percent_pass_filter": 0.143}, "0:0:0:39:212": {"defined_list": ["tuza"], "percent_pass_filter": 0.122}, "0:0:0:39:255": {"defined_list": ["boun"], "percent_pass_filter": 0.144}, "0:0:0:39:316": {"defined_list": ["neif"], "percent_pass_filter": 0.118}, "0:0:0:39:366": {"defined_list": ["java"], "percent_pass_filter": 0.198}}