{"0:0:0:2:5": {"defined_list": ["week"], "percent_pass_filter": 0.133}, "0:0:0:2:25": {"defined_list": ["togs"], "percent_pass_filter": 0.139}, "0:0:0:2:60": {"defined_list": ["mack"], "percent_pass_filter": 0.191}, "0:0:0:2:113": {"defined_list": ["yale"], "percent_pass_filter": 0.115}, "0:0:0:2:127": {"defined_list": ["boho"], "percent_pass_filter": 0.093}, "0:0:0:2:136": {"defined_list": ["glenn"], "percent_pass_filter": 0.163}, "0:0:0:2:142": {"defined_list": ["oord"], "percent_pass_filter": 0.153}, "0:0:0:2:161": {"defined_list": ["peda"], "percent_pass_filter": 0.132}, "0:0:0:2:180": {"defined_list": ["moss"], "percent_pass_filter": 0.125}, "0:0:0:2:190": {"defined_list": ["awfu"], "percent_pass_filter": 0.119}, "0:0:0:2:202": {"defined_list": ["jube"], "percent_pass_filter": 0.081}, "0:0:0:2:225": {"defined_list": ["keep"], "percent_pass_filter": 0.138}, "0:0:0:2:247": {"defined_list": ["artel"], "percent_pass_filter": 0.157}, "0:0:0:2:265": {"defined_list": ["peto"], "percent_pass_filter": 0.168}, "0:0:0:2:271": {"defined_list": ["camb"], "percent_pass_filter": 0.116}, "0:0:0:2:310": {"defined_list": ["vita"], "percent_pass_filter": 0.119}, "0:0:0:2:366": {"defined_list": ["tilt"], "percent_pass_filter": 0.148}, "0:0:0:2:382": {"defined_list": ["unie"], "percent_pass_filter": 0.172}}